chainlet/__about__.py
chainlet/__init__.py
chainlet/chainlink.py
chainlet/dataflow.py
chainlet/driver.py
chainlet/funclink.py
chainlet/genlink.py
chainlet/protolink.py
chainlet/utility.py
chainlet/wrapper.py
chainlet/compat/__init__.py
chainlet/compat/python2.py
chainlet/compat/python3.py
chainlet-1.1.0.dist-info/DESCRIPTION.rst
chainlet-1.1.0.dist-info/METADATA
chainlet-1.1.0.dist-info/RECORD
chainlet-1.1.0.dist-info/WHEEL
chainlet-1.1.0.dist-info/metadata.json
chainlet-1.1.0.dist-info/output_13.json.webarchive
chainlet-1.1.0.dist-info/top_level.txt
chainlet_unittests/__init__.py
chainlet_unittests/_utility.py
chainlet_unittests/utility.py
chainlet_unittests/chainlet/__init__.py
chainlet_unittests/chainlet/compat.py
chainlet_unittests/chainlet/driver.py
chainlet_unittests/chainlet/funclink.py
chainlet_unittests/chainlet/genlink.py
chainlet_unittests/chainlet/utility.py
chainlet_unittests/dataflow/__init__.py
chainlet_unittests/dataflow/iteration.py
chainlet_unittests/dataflow/mergefork.py
chainlet_unittests/dataflow/nested.py
chainlet_unittests/dataflow/primitives.py
chainlet_unittests/grammar/__init__.py
chainlet_unittests/grammar/linker.py
chainlet_unittests/linklet/__init__.py
chainlet_unittests/linklet/generators.py
chainlet_unittests/primitives/__init__.py
chainlet_unittests/primitives/test_genlink.py
chainlet_unittests/test_chainlet/__init__.py
chainlet_unittests/test_chainlet/test_compat.py
chainlet_unittests/test_chainlet/test_driver.py
chainlet_unittests/test_chainlet/test_funclink.py
chainlet_unittests/test_chainlet/test_genlink.py
chainlet_unittests/test_chainlet/test_protolink.py
chainlet_unittests/test_chainlet/test_utility.py
chainlet_unittests/test_dataflow/__init__.py
chainlet_unittests/test_dataflow/test_iteration.py
chainlet_unittests/test_dataflow/test_mergefork.py
chainlet_unittests/test_dataflow/test_nested.py
chainlet_unittests/test_dataflow/test_primitives.py
chainlet_unittests/test_grammar/__init__.py
chainlet_unittests/test_grammar/test_linker.py
