Metadata-Version: 2.0
Name: chainlet
Version: 1.1.0
Summary: Framework for linking generators/iterators to processing chains, trees and graphs
Home-page: https://github.com/maxfischer2781/chainlet
Author: Max Fischer
Author-email: maxfischer2781@gmail.com
License: MIT
Keywords: chaining generator coroutine stream pipeline chain bind tree graph
Platform: UNKNOWN
Classifier: Development Status :: 5 - Production/Stable
Classifier: Intended Audience :: Developers
Classifier: Intended Audience :: System Administrators
Classifier: License :: OSI Approved :: MIT License
Classifier: Topic :: System :: Monitoring
Classifier: Programming Language :: Python :: 2
Classifier: Programming Language :: Python :: 2.4
Classifier: Programming Language :: Python :: 2.5
Classifier: Programming Language :: Python :: 2.6
Classifier: Programming Language :: Python :: 2.7
Classifier: Programming Language :: Python :: 3
Classifier: Programming Language :: Python :: 3.2
Classifier: Programming Language :: Python :: 3.3
Classifier: Programming Language :: Python :: 3.4
Classifier: Programming Language :: Python :: 3.5
Classifier: Programming Language :: Python :: 3.6
